[
  {
    "title": "Gatinha chorosa sentimental",
    "date": "2026-04-05",
    "text": "Uma garota linda chorando pra voltar pra casa sem o namorado, tadinha, lindinha inha inha",
    "img": "https://raw.githubusercontent.com/KallebySchultz/vivi/main/uploads/img-1775429359733-fscuan.jpg"
  },
  {
    "title": "UwU",
    "date": "2026-03-15",
    "text": "kimi no toriko ni natte shimaeba kitto",
    "img": "https://raw.githubusercontent.com/KallebySchultz/vivi/main/uploads/img-1775182152449-xf51qz.jpg"
  },
  {
    "title": "Uma mosca gatinha ;)",
    "date": "2026-02-17",
    "text": "Foto enviada em uma terça feira, no final da manhã pela mosca mais bela do mundo.",
    "img": "https://raw.githubusercontent.com/KallebySchultz/vivi/main/uploads/img-1775176914762-t9s51a.jpg"
  }
]